setup.cfg
setup.py
kalibro_client/__init__.py
kalibro_client/base.py
kalibro_client/errors.py
kalibro_client.egg-info/PKG-INFO
kalibro_client.egg-info/SOURCES.txt
kalibro_client.egg-info/dependency_links.txt
kalibro_client.egg-info/not-zip-safe
kalibro_client.egg-info/requires.txt
kalibro_client.egg-info/top_level.txt
kalibro_client/configurations/__init__.py
kalibro_client/configurations/base.py
kalibro_client/configurations/kalibro_configuration.py
kalibro_client/configurations/kalibro_range.py
kalibro_client/configurations/metric_configuration.py
kalibro_client/configurations/range_snapshot.py
kalibro_client/configurations/reading.py
kalibro_client/configurations/reading_group.py
kalibro_client/configurations/statistic.py
kalibro_client/miscellaneous/__init__.py
kalibro_client/miscellaneous/compound_metric.py
kalibro_client/miscellaneous/date_metric_result.py
kalibro_client/miscellaneous/date_module_result.py
kalibro_client/miscellaneous/granularity.py
kalibro_client/miscellaneous/metric.py
kalibro_client/miscellaneous/native_metric.py
kalibro_client/processor/__init__.py
kalibro_client/processor/base.py
kalibro_client/processor/kalibro_module.py
kalibro_client/processor/metric_collector_details.py
kalibro_client/processor/metric_result.py
kalibro_client/processor/module_result.py
kalibro_client/processor/process_time.py
kalibro_client/processor/processing.py
kalibro_client/processor/project.py
kalibro_client/processor/repository.py
tests/__init__.py
tests/factories.py
tests/helpers.py
tests/test_base.py
tests/test_config.py
tests/test_configurations.py
tests/test_miscellaneous.py
tests/test_processor.py