Metadata-Version: 1.1
Name: kalibro-client
Version: 1.3.0.1
Summary: A http client for the Kalibro services.
Home-page: https://github.com/mezuro/kalibro_client_py
Author: Rafael Reggiani Manzo
Author-email: rr.manzo@gmail.com
License: LGPLv3
Platform: UNKNOWN
Classifier: Intended Audience :: Developers
Classifier: Topic :: Software Development
